op_data/__init__.py
op_data/database.py
op_data/date.py
op_data/op_time.py
op_data-0.0.4.dist-info/METADATA
op_data-0.0.4.dist-info/WHEEL
op_data-0.0.4.dist-info/top_level.txt
op_data-0.0.4.dist-info/RECORD
