Metadata-Version: 2.1
Name: op-data
Version: 0.0.4
Summary: operate kinds of databases
Home-page: https://gitee.com/shuzhiwei1/op_data
Author: shuzhiwei
Author-email: 1065537421@qq.com
Classifier: Programming Language :: Python :: 3
Classifier: License :: OSI Approved :: MIT License
Classifier: Operating System :: OS Independent
Requires-Python: >=3.6
Requires-Dist: bleach (==5.0.1)
Requires-Dist: certifi (==2022.9.14)
Requires-Dist: charset-normalizer (==2.1.1)
Requires-Dist: commonmark (==0.9.1)
Requires-Dist: cx-Oracle (==8.3.0)
Requires-Dist: docutils (==0.19)
Requires-Dist: greenlet (==1.1.3)
Requires-Dist: idna (==3.4)
Requires-Dist: importlib-metadata (==4.12.0)
Requires-Dist: jaraco.classes (==3.2.2)
Requires-Dist: keyring (==23.9.1)
Requires-Dist: more-itertools (==8.14.0)
Requires-Dist: numpy (==1.23.3)
Requires-Dist: pandas (==1.4.4)
Requires-Dist: pkginfo (==1.8.3)
Requires-Dist: Pygments (==2.13.0)
Requires-Dist: PyMySQL (==1.0.2)
Requires-Dist: python-dateutil (==2.8.2)
Requires-Dist: pytz (==2022.2.1)
Requires-Dist: pywin32-ctypes (==0.2.0)
Requires-Dist: readme-renderer (==37.1)
Requires-Dist: requests (==2.28.1)
Requires-Dist: requests-toolbelt (==0.9.1)
Requires-Dist: rfc3986 (==2.0.0)
Requires-Dist: rich (==12.5.1)
Requires-Dist: six (==1.16.0)
Requires-Dist: SQLAlchemy (==1.4.35)
Requires-Dist: twine (==4.0.1)
Requires-Dist: urllib3 (==1.26.12)
Requires-Dist: webencodings (==0.5.1)
Requires-Dist: zipp (==3.8.1)
